deformacion_lib/__init__.py
deformacion_lib/estructura3d.py
deformacion_lib/tensile.py
deformacion_lib-0.1.0.dist-info/LICENSE
deformacion_lib-0.1.0.dist-info/METADATA
deformacion_lib-0.1.0.dist-info/WHEEL
deformacion_lib-0.1.0.dist-info/top_level.txt
deformacion_lib-0.1.0.dist-info/RECORD
