Metadata-Version: 2.1
Name: deformacion_lib
Version: 0.1.0
Summary: Library for deformation analysis in tensile tests and 3D structures
Author: Martin Esteban, Oier Labeaga, Malen Ubiria, Eneko Urrutia
Author-email: martin.esteban@alumni.mondragon.edu, oier.labeaga@alumni.mondragon.edu, malen.ubiria@alumni.mondragon.edu, eneko.urrutia@alumni.mondragon.edu
Classifier: Programming Language :: Python :: 3
Classifier: License :: OSI Approved :: MIT License
Classifier: Operating System :: OS Independent
Requires-Python: >=3.8
License-File: LICENSE
Requires-Dist: opencv-python >=4.5.0
Requires-Dist: numpy >=1.19.0
Requires-Dist: matplotlib >=3.3.0
Requires-Dist: pandas >=1.1.0
Requires-Dist: Pillow >=8.0.0
Requires-Dist: imageio >=2.9.0
